[
    {"name": "Tutorials",
     "folder": "tutorials",
     "pages": [
         {"file": "tutorialArithmetic",
          "name": "IntervalArithmetic.jl"},
         {"file": "tutorialRootFinding",
          "name": "IntervalRootFinding.jl"},
         {"file": "tutorialConstraintProgramming",
          "name": "IntervalConstraintProgramming.jl"},
         {"file": "tutorialOptimisation",
          "name": "IntervalOptimisation.jl"}
     ]},

    {"name": "Applications",
     "folder": "howTo",
     "pages": [
        {"file": "funcRange",
         "name": "Rigorous computation of function range"},
        {"file": "funcRangePluto",
        "name": "Rigorous computation of function range PLUTO"},
         {"file": "rigorousPi",
          "name": "Rigorous approximation of π"}
     ]},

     {"name": "Explanations",
        "folder": "explanations",
        "pages": [
           {"file": "intervalAnalysisIntro",
            "name": "Introduction to interval analysis"}
        ]},

        {"name": "API",
            "folder": "apiDocs",
            "pages": [
               {"file": "apiIntervalArithmetic",
                "name": "IntervalArithmetic.jl"}
            ]}
]